jk_version/BaseVersionConstraint.py
jk_version/Version.py
jk_version/VersionConstraintAND.py
jk_version/VersionConstraintEQ.py
jk_version/VersionConstraintGE.py
jk_version/VersionConstraintGT.py
jk_version/VersionConstraintLE.py
jk_version/VersionConstraintLT.py
jk_version/VersionConstraintNE.py
jk_version/VersionConstraintOR.py
jk_version/_ConstraintDeserializer.py
jk_version/__init__.py
jk_version-0.2024.7.24.dist-info/WHEEL
jk_version-0.2024.7.24.dist-info/METADATA
jk_version-0.2024.7.24.dist-info/RECORD
