Metadata-Version: 2.1
Name: jk_version
Version: 0.2024.7.24
Summary: This python module provides a version class. Instances of this class may be used in representing and version numbers and compare them.
Keywords: version,versioning
Author-email: Jürgen Knauth <pubsrc@binary-overflow.de>
Maintainer-email: Jürgen Knauth <pubsrc@binary-overflow.de>
Requires-Python: >=3.8
Classifier: Development Status :: 5 - Production/Stable
Classifier: License :: OSI Approved :: Apache Software License
Classifier: Programming Language :: Python :: 3
